MANIFEST.in
README.md
setup.py
collect/__init__.py
collect/settings.py
collect.egg-info/PKG-INFO
collect.egg-info/SOURCES.txt
collect.egg-info/dependency_links.txt
collect.egg-info/requires.txt
collect.egg-info/top_level.txt
collect/tests/__init__.py
collect/tests/__main__.py
collect/tests/run.py