Metadata-Version: 1.0
Name: collect
Version: 0.1.1
Summary: Python library for collecting data at collect.io
Home-page: http://collect.io/libraries/python/
Author: Philipp Bosch
Author-email: hello@pb.io
License: http://philippbosch.mit-license.org/
Platform: UNKNOWN
Classifier: Development Status :: 3 - Alpha
Classifier: License :: OSI Approved :: MIT License
Classifier: Intended Audience :: Science/Research
Classifier: Programming Language :: Python :: 2.7
Classifier: Topic :: Database
Classifier: Topic :: Scientific/Engineering :: Information Analysis
Classifier: Topic :: Scientific/Engineering :: Visualization
Classifier: Topic :: Utilities
